sphinx_table_support/__init__.py
sphinx_table_support/_version.py
sphinx_table_support-0.0.1.dist-info/METADATA
sphinx_table_support-0.0.1.dist-info/WHEEL
sphinx_table_support-0.0.1.dist-info/licenses/LICENSE
sphinx_table_support-0.0.1.dist-info/RECORD
