Metadata-Version: 2.4
Name: sphinx-table-support
Version: 0.0.1
Summary: A Sphinx extension that provides a collection of directives for different table languages.
Author-email: Dennis den Ouden-van der Horst <d.denouden-vanderhorst@tudelft.nl>
License: MIT License
License-File: LICENSE
Requires-Python: >=3.10
Requires-Dist: sphinx
